Metadata-Version: 1.1
Name: img-percent-diff
Version: 0.1.0
Summary: Calculates the percent area that two images differ
Home-page: https://github.com/cpc/img-percent-diff
Author: Mike Charles
Author-email: mike.charles@noaa.gov
License: CC
Keywords: img-percent-diff
Platform: UNKNOWN
Classifier: Development Status :: 1 - Planning
Classifier: Environment :: Console
Classifier: Intended Audience :: Science/Research
Classifier: Programming Language :: Python
Classifier: Programming Language :: Python :: 3
Classifier: Operating System :: OS Independent
Classifier: Topic :: Scientific/Engineering :: Atmospheric Science
Classifier: License :: CC0 1.0 Universal (CC0 1.0) Public Domain Dedication
